ezcalculator/__init__.py
ezcalculator-0.0.2.dist-info/LICENSE.txt
ezcalculator-0.0.2.dist-info/METADATA
ezcalculator-0.0.2.dist-info/WHEEL
ezcalculator-0.0.2.dist-info/top_level.txt
ezcalculator-0.0.2.dist-info/RECORD
