Metadata-Version: 2.1
Name: ezcalculator
Version: 0.0.2
Summary: A very basic calculator
Home-page: 
Author: Aan
Author-email: aansyawaluddin2003@edublocks.org
License: MIT
Keywords: calculator
Classifier: Development Status :: 5 - Production/Stable
Classifier: Intended Audience :: Education
Classifier: Operating System :: Microsoft :: Windows :: Windows 10
Classifier: License :: OSI Approved :: MIT License
Classifier: Programming Language :: Python :: 3
License-File: LICENSE.txt
